jsonschema_rs/__init__.py
jsonschema_rs/__init__.pyi
jsonschema_rs/jsonschema_rs.pypy311-pp73-aarch64-linux-gnu.so
jsonschema_rs/py.typed
jsonschema_rs-0.40.4.dist-info/METADATA
jsonschema_rs-0.40.4.dist-info/WHEEL
jsonschema_rs-0.40.4.dist-info/RECORD
