Metadata-Version: 2.4
Name: jsonschema_rs
Version: 0.40.4
Classifier: Development Status :: 4 - Beta
Classifier: Intended Audience :: Developers
Classifier: License :: OSI Approved :: MIT License
Classifier: Operating System :: OS Independent
Classifier: Programming Language :: Python :: 3
Classifier: Programming Language :: Python :: 3 :: Only
Classifier: Programming Language :: Python :: 3.10
Classifier: Programming Language :: Python :: 3.11
Classifier: Programming Language :: Python :: 3.12
Classifier: Programming Language :: Python :: 3.13
Classifier: Programming Language :: Python :: 3.14
Classifier: Programming Language :: Python :: Implementation :: CPython
Classifier: Programming Language :: Python :: Implementation :: PyPy
Classifier: Programming Language :: Rust
Classifier: Topic :: File Formats :: JSON :: JSON Schema
Requires-Dist: fastjsonschema>=2.20.0 ; extra == 'bench'
Requires-Dist: jsonschema>=4.23.0 ; extra == 'bench'
Requires-Dist: pytest-benchmark>=4.0.0 ; extra == 'bench'
Requires-Dist: flask>=2.2.5 ; extra == 'tests'
Requires-Dist: hypothesis>=6.79.4 ; extra == 'tests'
Requires-Dist: pytest>=7.4.4 ; extra == 'tests'
Provides-Extra: bench
Provides-Extra: tests
Summary: A high-performance JSON Schema validator for Python
Keywords: jsonschema,validation,rust
Author-email: Dmitry Dygalo <dmitry@dygalo.dev>
Maintainer-email: Dmitry Dygalo <dmitry@dygalo.dev>
License: MIT
Requires-Python: >=3.10
Project-URL: Bug Tracker, https://github.com/Stranger6667/jsonschema/issues
Project-URL: Changelog, https://github.com/Stranger6667/jsonschema/blob/master/crates/jsonschema-py/CHANGELOG.md
Project-URL: Funding, https://github.com/sponsors/Stranger6667
Project-URL: Homepage, https://github.com/Stranger6667/jsonschema/tree/master/crates/jsonschema-py
Project-URL: Source, https://github.com/Stranger6667/jsonschema
